rbash/__init__.py
rbash/cli.py
rbash/remote.py
rbash-2.0.0.dist-info/licenses/LICENSE
rbash-2.0.0.dist-info/METADATA
rbash-2.0.0.dist-info/WHEEL
rbash-2.0.0.dist-info/top_level.txt
rbash-2.0.0.dist-info/RECORD
